niui/__init__.py
niui/__main__.py
niui/helpers.py
niui/api/__init__.py
niui/api/data.py
niui/api/error.py
niui/api/types.py
niui/api/can/__init__.py
niui/api/can/bus.py
niui/api/can/listeners.py
niui/api/can/messages.py
niui/api/can/read.py
niui/api/can/write.py
niui/api/files/__init__.py
niui/api/files/config.py
niui/api/files/firmware.py
niui/api/files/json.py
niui/api/files/project.py
niui/api/routes/__init__.py
niui/api/routes/boxes.py
niui/api/routes/configurables.py
niui/api/routes/configurations.py
niui/api/routes/firmwares.py
niui/api/routes/projects.py
niui/templates/index.css
niui/templates/index.html
niui/templates/index.js
niui-1.2.1.dist-info/LICENSE
niui-1.2.1.dist-info/METADATA
niui-1.2.1.dist-info/WHEEL
niui-1.2.1.dist-info/top_level.txt
niui-1.2.1.dist-info/RECORD
