Metadata-Version: 2.1
Name: niui
Version: 1.2.1
Summary: Nimu UI Configurator
Author-email: Nordic Inertial <timo.pihlstrom@nordicinertial.com>
Project-URL: Homepage, https://dev.azure.com/nordic-inertial/ni-public/_git/niui
Classifier: Programming Language :: Python :: 3
Classifier: License :: OSI Approved :: MIT License
Classifier: Operating System :: OS Independent
Requires-Python: >=3.7
License-File: LICENSE
Requires-Dist: Flask ==2.3.2
Requires-Dist: python-can ==4.2.1
